aqt/__init__.py
aqt/__main__.py
aqt/archives.py
aqt/commercial.py
aqt/exceptions.py
aqt/helper.py
aqt/installer.py
aqt/logging.ini
aqt/metadata.py
aqt/settings.ini
aqt/updater.py
aqt/version.py
aqtinstall-3.2.1.dist-info/LICENSE
aqtinstall-3.2.1.dist-info/METADATA
aqtinstall-3.2.1.dist-info/WHEEL
aqtinstall-3.2.1.dist-info/entry_points.txt
aqtinstall-3.2.1.dist-info/top_level.txt
aqtinstall-3.2.1.dist-info/RECORD
