Metadata-Version: 2.2
Name: aqtinstall
Version: 3.2.1
Summary: Another unofficial Qt installer
Author-email: Hiroshi Miura <miurahr@linux.com>
License: MIT License
Project-URL: Documentation, https://aqtinstall.readthedocs.io/
Project-URL: Bug Tracker, https://github.com/miurahr/aqtinstall/issues
Project-URL: Wiki, https://github.com/miurahr/aqtinstall/wiki
Project-URL: Source, https://github.com/miurahr/aqtinstall
Project-URL: Changelog, https://aqtinstall.readthedocs.io/en/latest/CHANGELOG.html
Classifier: Development Status :: 4 - Beta
Classifier: Environment :: Console
Classifier: Environment :: X11 Applications :: Qt
Classifier: Intended Audience :: Developers
Classifier: License :: OSI Approved :: MIT License
Classifier: Operating System :: MacOS :: MacOS X
Classifier: Operating System :: Microsoft :: Windows
Classifier: Operating System :: POSIX
Classifier: Operating System :: POSIX :: Linux
Classifier: Programming Language :: Python
Classifier: Programming Language :: C++
Classifier: Topic :: Software Development
Classifier: Topic :: Software Development :: Libraries
Requires-Python: >=3.9
License-File: LICENSE
Requires-Dist: bs4
Requires-Dist: defusedxml
Requires-Dist: humanize
Requires-Dist: patch-ng
Requires-Dist: py7zr>=0.22.0
Requires-Dist: requests>=2.31.0
Requires-Dist: semantic-version
Requires-Dist: texttable
Provides-Extra: test
Requires-Dist: pytest>=6.0; extra == "test"
Requires-Dist: pytest-pep8; extra == "test"
Requires-Dist: pytest-cov; extra == "test"
Requires-Dist: pytest-remotedata>=0.4.1; extra == "test"
Requires-Dist: pytest-socket; extra == "test"
Requires-Dist: pytest-timeout; extra == "test"
Requires-Dist: pympler; extra == "test"
Provides-Extra: check
Requires-Dist: mypy>=1.10.0; extra == "check"
Requires-Dist: flake8<8.0.0,>=6.0.0; extra == "check"
Requires-Dist: flake8-black; extra == "check"
Requires-Dist: flake8-colors; extra == "check"
Requires-Dist: flake8-isort<7.0.0,>=6.0.0; extra == "check"
Requires-Dist: flake8-pyi; extra == "check"
Requires-Dist: flake8-typing-imports; extra == "check"
Requires-Dist: docutils; extra == "check"
Requires-Dist: check-manifest; extra == "check"
Requires-Dist: readme-renderer; extra == "check"
Requires-Dist: pygments; extra == "check"
Requires-Dist: packaging; extra == "check"
Requires-Dist: pylint; extra == "check"
Requires-Dist: types-requests; extra == "check"
Provides-Extra: docs
Requires-Dist: sphinx>=7.0; extra == "docs"
Requires-Dist: sphinx_rtd_theme>=1.3; extra == "docs"
Requires-Dist: sphinx-py3doc-enhanced-theme>=2.4; extra == "docs"
Provides-Extra: debug
Requires-Dist: pytest-leaks; extra == "debug"
